{
  "Client": {
    "Name": "Шиш Тетяна ",
    "MPhone": "380682825562",
    "ZIP": "",
    "Country": "Україна",
    "Region": "Житомирська",
    "City": "Коростишів",
    "Address": "вул. Гіршмана,16",
    "EMail": "das.dd43031@gmail.com"
  },
  "Options": {
    "SaleType": "1",
    "Comment": "Замовлення з інтернет-магазину",
    "OrderNumber": "213",
    "DeliveryCondition": "Нова Пошта",
    "DeliveryAddress": "Відділення №2 (до 30 кг): вул. Героїв Небесної Сотні, 56",
    "OrderDate": "2024-12-16T13:35:21.568Z"
  },
  "Goods": [
    {
      "GoodID": "11",
      "Price": 565,
      "Count": 1
    }
  ]
}